apimaticcalculator/__init__.py
apimaticcalculator/api_helper.py
apimaticcalculator/apimaticcalculator_client.py
apimaticcalculator/configuration.py
apimaticcalculator/controllers/__init__.py
apimaticcalculator/controllers/base_controller.py
apimaticcalculator/controllers/simple_calculator_controller.py
apimaticcalculator/exceptions/__init__.py
apimaticcalculator/exceptions/api_exception.py
apimaticcalculator/http/__init__.py
apimaticcalculator/http/http_call_back.py
apimaticcalculator/http/http_method_enum.py
apimaticcalculator/http/http_request.py
apimaticcalculator/http/http_response.py
apimaticcalculator/models/__init__.py
apimaticcalculator/models/operation_type_enum.py
apimaticcalculator/utilities/__init__.py
apimaticcalculator/utilities/file_wrapper.py
fuller_ryan_sdk-6.8.8.dist-info/LICENSE
fuller_ryan_sdk-6.8.8.dist-info/METADATA
fuller_ryan_sdk-6.8.8.dist-info/WHEEL
fuller_ryan_sdk-6.8.8.dist-info/top_level.txt
fuller_ryan_sdk-6.8.8.dist-info/RECORD
