Metadata-Version: 2.1
Name: fuller-ryan-sdk
Version: 6.8.8
Summary: Corporis do inventor
Author-email: Warren Johns <siqyvy@mailinator.com>
Project-URL: Documentation, https://www.mygipycejacyw.me.uk
Requires-Python: >=3.7
License-File: LICENSE
Requires-Dist: apimatic-core >=0.2.15,~=0.2.0
Requires-Dist: apimatic-core-interfaces >=0.1.5,~=0.1.0
Requires-Dist: apimatic-requests-client-adapter >=0.1.6,~=0.1.0
Provides-Extra: testutils
Requires-Dist: pytest >=7.2.2 ; extra == 'testutils'
